Metadata-Version: 2.1
Name: bind2samba
Version: 1.0.3
Summary: Converts a bind zone file to samba-tool invocations
Home-page: https://github.com/eveith/bind2samba
Author: Eric MSP Veith
Author-email: eveith@binericien.org
License: UNKNOWN
Project-URL: Bug Tracker, https://github.com/eveith/bind2samba/issues
Platform: UNKNOWN
Classifier: License :: OSI Approved :: BSD License
Classifier: Development Status :: 5 - Production/Stable
Classifier: Programming Language :: Python :: 3
Classifier: Environment :: Console
Classifier: Operating System :: POSIX :: Linux
Classifier: Intended Audience :: System Administrators
Requires-Python: >=3.6, <4
